{"repo":"apex/apex","starred_at":"2015-12-19T23:55:31Z","login":"ashaffer","id":1871136,"node_id":"MDQ6VXNlcjE4NzExMzY=","html_url":"https://github.com/ashaffer","type":"User","site_admin":false}
{"repo":"apex/apex","starred_at":"2015-12-19T23:55:40Z","login":"yields","id":1661587,"node_id":"MDQ6VXNlcjE2NjE1ODc=","html_url":"https://github.com/yields","type":"User","site_admin":false}
{"repo":"apex/apex","starred_at":"2015-12-20T00:00:49Z","login":"AgtLucas","id":1909761,"node_id":"MDQ6VXNlcjE5MDk3NjE=","html_url":"https://github.com/AgtLucas","type":"User","site_admin":false}
{"repo":"apex/apex","starred_at":"2015-12-20T00:03:53Z","login":"tejasmanohar","id":5959235,"node_id":"MDQ6VXNlcjU5NTkyMzU=","html_url":"https://github.com/tejasmanohar","type":"User","site_admin":false}
{"repo":"apex/apex","starred_at":"2015-12-20T00:12:35Z","login":"nowk","id":74525,"node_id":"MDQ6VXNlcjc0NTI1","html_url":"https://github.com/nowk","type":"User","site_admin":false}
{"repo":"apex/apex","starred_at":"2015-12-20T00:37:46Z","login":"ZECTBynmo","id":1222872,"node_id":"MDQ6VXNlcjEyMjI4NzI=","html_url":"https://github.com/ZECTBynmo","type":"User","site_admin":false}
{"repo":"apex/apex","starred_at":"2015-12-20T01:02:03Z","login":"NoumanSaleem","id":694071,"node_id":"MDQ6VXNlcjY5NDA3MQ==","html_url":"https://github.com/NoumanSaleem","type":"User","site_admin":false}
{"repo":"apex/apex","starred_at":"2015-12-20T01:12:19Z","login":"nickpisacane","id":6256770,"node_id":"MDQ6VXNlcjYyNTY3NzA=","html_url":"https://github.com/nickpisacane","type":"User","site_admin":false}
{"repo":"apex/apex","starred_at":"2015-12-20T01:18:26Z","login":"bentranter","id":5421627,"node_id":"MDQ6VXNlcjU0MjE2Mjc=","html_url":"https://github.com/bentranter","type":"User","site_admin":false}
{"repo":"apex/apex","starred_at":"2015-12-20T01:23:49Z","login":"imjerrybao","id":11003906,"node_id":"MDQ6VXNlcjExMDAzOTA2","html_url":"https://github.com/imjerrybao","type":"User","site_admin":false}
{"repo":"apex/apex","starred_at":"2015-12-20T01:26:58Z","login":"avelino","id":31996,"node_id":"MDQ6VXNlcjMxOTk2","html_url":"https://github.com/avelino","type":"User","site_admin":false}
{"repo":"apex/apex","starred_at":"2015-12-20T01:29:32Z","login":"joshrtay","id":132602,"node_id":"MDQ6VXNlcjEzMjYwMg==","html_url":"https://github.com/joshrtay","type":"User","site_admin":false}
{"repo":"apex/apex","starred_at":"2015-12-20T02:40:32Z","login":"chentsulin","id":3382565,"node_id":"MDQ6VXNlcjMzODI1NjU=","html_url":"https://github.com/chentsulin","type":"User","site_admin":false}
{"repo":"apex/apex","starred_at":"2015-12-20T02:45:47Z","login":"slattery","id":1829326,"node_id":"MDQ6VXNlcjE4MjkzMjY=","html_url":"https://github.com/slattery","type":"User","site_admin":false}
{"repo":"apex/apex","starred_at":"2015-12-20T03:51:41Z","login":"deedubs","id":10067,"node_id":"MDQ6VXNlcjEwMDY3","html_url":"https://github.com/deedubs","type":"User","site_admin":false}
{"repo":"apex/apex","starred_at":"2015-12-20T04:28:27Z","login":"matthewmueller","id":170299,"node_id":"MDQ6VXNlcjE3MDI5OQ==","html_url":"https://github.com/matthewmueller","type":"User","site_admin":false}
{"repo":"apex/apex","starred_at":"2015-12-20T04:29:30Z","login":"zhiyelee","id":681150,"node_id":"MDQ6VXNlcjY4MTE1MA==","html_url":"https://github.com/zhiyelee","type":"User","site_admin":false}
{"repo":"apex/apex","starred_at":"2015-12-20T04:36:45Z","login":"dapithor","id":5496515,"node_id":"MDQ6VXNlcjU0OTY1MTU=","html_url":"https://github.com/dapithor","type":"User","site_admin":false}
{"repo":"apex/apex","starred_at":"2015-12-20T04:45:54Z","login":"calvinfo","id":487539,"node_id":"MDQ6VXNlcjQ4NzUzOQ==","html_url":"https://github.com/calvinfo","type":"User","site_admin":false}
{"repo":"apex/apex","starred_at":"2015-12-20T05:43:50Z","login":"CYBAI","id":6782666,"node_id":"MDQ6VXNlcjY3ODI2NjY=","html_url":"https://github.com/CYBAI","type":"User","site_admin":false}
{"repo":"apex/apex","starred_at":"2015-12-20T06:02:10Z","login":"alfg","id":702541,"node_id":"MDQ6VXNlcjcwMjU0MQ==","html_url":"https://github.com/alfg","type":"User","site_admin":false}
{"repo":"apex/apex","starred_at":"2015-12-20T07:05:50Z","login":"bencevans","id":638535,"node_id":"MDQ6VXNlcjYzODUzNQ==","html_url":"https://github.com/bencevans","type":"User","site_admin":false}
{"repo":"apex/apex","starred_at":"2015-12-20T08:01:57Z","login":"danieljuhl","id":2785418,"node_id":"MDQ6VXNlcjI3ODU0MTg=","html_url":"https://github.com/danieljuhl","type":"User","site_admin":false}
{"repo":"apex/apex","starred_at":"2015-12-20T10:10:06Z","login":"dan-dr","id":6669808,"node_id":"MDQ6VXNlcjY2Njk4MDg=","html_url":"https://github.com/dan-dr","type":"User","site_admin":false}
{"repo":"apex/apex","starred_at":"2015-12-20T11:09:20Z","login":"jamesrwhite","id":640960,"node_id":"MDQ6VXNlcjY0MDk2MA==","html_url":"https://github.com/jamesrwhite","type":"User","site_admin":false}
{"repo":"apex/apex","starred_at":"2015-12-20T13:39:38Z","login":"jney","id":747,"node_id":"MDQ6VXNlcjc0Nw==","html_url":"https://github.com/jney","type":"User","site_admin":false}
{"repo":"apex/apex","starred_at":"2015-12-20T14:42:10Z","login":"billyct","id":1612364,"node_id":"MDQ6VXNlcjE2MTIzNjQ=","html_url":"https://github.com/billyct","type":"User","site_admin":false}
{"repo":"apex/apex","starred_at":"2015-12-20T14:52:12Z","login":"mthenw","id":455261,"node_id":"MDQ6VXNlcjQ1NTI2MQ==","html_url":"https://github.com/mthenw","type":"User","site_admin":false}
{"repo":"apex/apex","starred_at":"2015-12-20T15:41:07Z","login":"vic","id":331,"node_id":"MDQ6VXNlcjMzMQ==","html_url":"https://github.com/vic","type":"User","site_admin":false}
{"repo":"apex/apex","starred_at":"2015-12-20T17:50:09Z","login":"hoppula","id":1070425,"node_id":"MDQ6VXNlcjEwNzA0MjU=","html_url":"https://github.com/hoppula","type":"User","site_admin":false}
