{"repo":"chmln/flatpickr","starred_at":"2015-09-04T16:35:13Z","login":"olegberman","id":6267340,"node_id":"MDQ6VXNlcjYyNjczNDA=","html_url":"https://github.com/olegberman","type":"User","site_admin":false}
{"repo":"chmln/flatpickr","starred_at":"2015-09-15T01:59:19Z","login":"rafaelrenanpacheco","id":12160864,"node_id":"MDQ6VXNlcjEyMTYwODY0","html_url":"https://github.com/rafaelrenanpacheco","type":"User","site_admin":false}
{"repo":"chmln/flatpickr","starred_at":"2015-09-18T17:37:04Z","login":"adaniello","id":242423,"node_id":"MDQ6VXNlcjI0MjQyMw==","html_url":"https://github.com/adaniello","type":"User","site_admin":false}
{"repo":"chmln/flatpickr","starred_at":"2015-09-19T03:07:06Z","login":"wuqi","id":1532967,"node_id":"MDQ6VXNlcjE1MzI5Njc=","html_url":"https://github.com/wuqi","type":"User","site_admin":false}
{"repo":"chmln/flatpickr","starred_at":"2015-10-21T11:51:36Z","login":"dsklyadnev","id":2197348,"node_id":"MDQ6VXNlcjIxOTczNDg=","html_url":"https://github.com/dsklyadnev","type":"User","site_admin":false}
{"repo":"chmln/flatpickr","starred_at":"2015-10-27T08:00:27Z","login":"devinchen","id":1542916,"node_id":"MDQ6VXNlcjE1NDI5MTY=","html_url":"https://github.com/devinchen","type":"User","site_admin":false}
{"repo":"chmln/flatpickr","starred_at":"2015-12-02T18:24:41Z","login":"fabricionaweb","id":15933,"node_id":"MDQ6VXNlcjE1OTMz","html_url":"https://github.com/fabricionaweb","type":"User","site_admin":false}
{"repo":"chmln/flatpickr","starred_at":"2015-12-18T11:29:17Z","login":"anthonyjb","id":3046287,"node_id":"MDQ6VXNlcjMwNDYyODc=","html_url":"https://github.com/anthonyjb","type":"User","site_admin":false}
{"repo":"chmln/flatpickr","starred_at":"2016-01-14T20:19:44Z","login":"leigeber","id":255097,"node_id":"MDQ6VXNlcjI1NTA5Nw==","html_url":"https://github.com/leigeber","type":"User","site_admin":false}
{"repo":"chmln/flatpickr","starred_at":"2016-01-28T09:37:00Z","login":"jakkor","id":2526307,"node_id":"MDQ6VXNlcjI1MjYzMDc=","html_url":"https://github.com/jakkor","type":"User","site_admin":false}
{"repo":"chmln/flatpickr","starred_at":"2016-01-29T08:46:05Z","login":"SerbanC","id":1150246,"node_id":"MDQ6VXNlcjExNTAyNDY=","html_url":"https://github.com/SerbanC","type":"User","site_admin":false}
{"repo":"chmln/flatpickr","starred_at":"2016-02-04T20:38:10Z","login":"wiljanslofstra","id":665755,"node_id":"MDQ6VXNlcjY2NTc1NQ==","html_url":"https://github.com/wiljanslofstra","type":"User","site_admin":false}
{"repo":"chmln/flatpickr","starred_at":"2016-02-08T16:33:24Z","login":"mintbridge","id":32777,"node_id":"MDQ6VXNlcjMyNzc3","html_url":"https://github.com/mintbridge","type":"User","site_admin":false}
{"repo":"chmln/flatpickr","starred_at":"2016-02-08T16:43:06Z","login":"rafi","id":147918,"node_id":"MDQ6VXNlcjE0NzkxOA==","html_url":"https://github.com/rafi","type":"User","site_admin":false}
{"repo":"chmln/flatpickr","starred_at":"2016-02-12T12:20:15Z","login":"NullVoxPopuli","id":199018,"node_id":"MDQ6VXNlcjE5OTAxOA==","html_url":"https://github.com/NullVoxPopuli","type":"User","site_admin":false}
{"repo":"chmln/flatpickr","starred_at":"2016-02-12T13:58:33Z","login":"timelyportfolio","id":837910,"node_id":"MDQ6VXNlcjgzNzkxMA==","html_url":"https://github.com/timelyportfolio","type":"User","site_admin":false}
{"repo":"chmln/flatpickr","starred_at":"2016-02-12T14:30:09Z","login":"SantoshSrinivas79","id":1036163,"node_id":"MDQ6VXNlcjEwMzYxNjM=","html_url":"https://github.com/SantoshSrinivas79","type":"User","site_admin":false}
{"repo":"chmln/flatpickr","starred_at":"2016-02-18T12:37:24Z","login":"richardwo","id":1397305,"node_id":"MDQ6VXNlcjEzOTczMDU=","html_url":"https://github.com/richardwo","type":"User","site_admin":false}
{"repo":"chmln/flatpickr","starred_at":"2016-02-19T04:27:26Z","login":"tomtomau","id":2062363,"node_id":"MDQ6VXNlcjIwNjIzNjM=","html_url":"https://github.com/tomtomau","type":"User","site_admin":false}
{"repo":"chmln/flatpickr","starred_at":"2016-03-02T13:25:49Z","login":"sergonius","id":6144993,"node_id":"MDQ6VXNlcjYxNDQ5OTM=","html_url":"https://github.com/sergonius","type":"User","site_admin":false}
{"repo":"chmln/flatpickr","starred_at":"2016-03-13T01:20:38Z","login":"jmas","id":90701,"node_id":"MDQ6VXNlcjkwNzAx","html_url":"https://github.com/jmas","type":"User","site_admin":false}
{"repo":"chmln/flatpickr","starred_at":"2016-03-14T13:31:22Z","login":"RocAlayo","id":2017006,"node_id":"MDQ6VXNlcjIwMTcwMDY=","html_url":"https://github.com/RocAlayo","type":"User","site_admin":false}
{"repo":"chmln/flatpickr","starred_at":"2016-03-18T09:12:19Z","login":"joacim-boive","id":270235,"node_id":"MDQ6VXNlcjI3MDIzNQ==","html_url":"https://github.com/joacim-boive","type":"User","site_admin":false}
{"repo":"chmln/flatpickr","starred_at":"2016-04-01T14:49:17Z","login":"yjchen","id":657231,"node_id":"MDQ6VXNlcjY1NzIzMQ==","html_url":"https://github.com/yjchen","type":"User","site_admin":false}
{"repo":"chmln/flatpickr","starred_at":"2016-04-04T08:49:37Z","login":"logikinc","id":7368491,"node_id":"MDQ6VXNlcjczNjg0OTE=","html_url":"https://github.com/logikinc","type":"User","site_admin":false}
{"repo":"chmln/flatpickr","starred_at":"2016-04-05T07:01:06Z","login":"think2011","id":3961388,"node_id":"MDQ6VXNlcjM5NjEzODg=","html_url":"https://github.com/think2011","type":"User","site_admin":false}
{"repo":"chmln/flatpickr","starred_at":"2016-04-08T14:01:20Z","login":"afnpires","id":5302351,"node_id":"MDQ6VXNlcjUzMDIzNTE=","html_url":"https://github.com/afnpires","type":"User","site_admin":false}
{"repo":"chmln/flatpickr","starred_at":"2016-04-12T02:47:39Z","login":"rwwagner90","id":2640861,"node_id":"MDQ6VXNlcjI2NDA4NjE=","html_url":"https://github.com/rwwagner90","type":"User","site_admin":false}
{"repo":"chmln/flatpickr","starred_at":"2016-04-13T15:49:06Z","login":"jamesdixon","id":110114,"node_id":"MDQ6VXNlcjExMDExNA==","html_url":"https://github.com/jamesdixon","type":"User","site_admin":false}
{"repo":"chmln/flatpickr","starred_at":"2016-04-14T10:27:45Z","login":"lambder","id":95941,"node_id":"MDQ6VXNlcjk1OTQx","html_url":"https://github.com/lambder","type":"User","site_admin":false}
