{"repo":"coursera-dl/coursera-dl","starred_at":"2012-03-21T21:07:15Z","login":"da3mon","id":1025,"node_id":"MDQ6VXNlcjEwMjU=","html_url":"https://github.com/da3mon","type":"User","site_admin":false}
{"repo":"coursera-dl/coursera-dl","starred_at":"2012-03-21T21:07:15Z","login":"ludwig","id":1056,"node_id":"MDQ6VXNlcjEwNTY=","html_url":"https://github.com/ludwig","type":"User","site_admin":false}
{"repo":"coursera-dl/coursera-dl","starred_at":"2012-03-21T21:07:15Z","login":"ajturner","id":1218,"node_id":"MDQ6VXNlcjEyMTg=","html_url":"https://github.com/ajturner","type":"User","site_admin":false}
{"repo":"coursera-dl/coursera-dl","starred_at":"2012-03-21T21:07:15Z","login":"mcroydon","id":1411,"node_id":"MDQ6VXNlcjE0MTE=","html_url":"https://github.com/mcroydon","type":"User","site_admin":false}
{"repo":"coursera-dl/coursera-dl","starred_at":"2012-03-21T21:07:15Z","login":"bmabey","id":1837,"node_id":"MDQ6VXNlcjE4Mzc=","html_url":"https://github.com/bmabey","type":"User","site_admin":false}
{"repo":"coursera-dl/coursera-dl","starred_at":"2012-03-21T21:07:15Z","login":"dandorman","id":2452,"node_id":"MDQ6VXNlcjI0NTI=","html_url":"https://github.com/dandorman","type":"User","site_admin":false}
{"repo":"coursera-dl/coursera-dl","starred_at":"2012-03-21T21:07:15Z","login":"namelessjon","id":2833,"node_id":"MDQ6VXNlcjI4MzM=","html_url":"https://github.com/namelessjon","type":"User","site_admin":false}
{"repo":"coursera-dl/coursera-dl","starred_at":"2012-03-21T21:07:15Z","login":"briandeweese","id":5341,"node_id":"MDQ6VXNlcjUzNDE=","html_url":"https://github.com/briandeweese","type":"User","site_admin":false}
{"repo":"coursera-dl/coursera-dl","starred_at":"2012-03-21T21:07:15Z","login":"ybakos","id":5502,"node_id":"MDQ6VXNlcjU1MDI=","html_url":"https://github.com/ybakos","type":"User","site_admin":false}
{"repo":"coursera-dl/coursera-dl","starred_at":"2012-03-21T21:07:15Z","login":"yrcjaya","id":5592,"node_id":"MDQ6VXNlcjU1OTI=","html_url":"https://github.com/yrcjaya","type":"User","site_admin":false}
{"repo":"coursera-dl/coursera-dl","starred_at":"2012-03-21T21:07:15Z","login":"christianromney","id":5679,"node_id":"MDQ6VXNlcjU2Nzk=","html_url":"https://github.com/christianromney","type":"User","site_admin":false}
{"repo":"coursera-dl/coursera-dl","starred_at":"2012-03-21T21:07:15Z","login":"fmeyer","id":5771,"node_id":"MDQ6VXNlcjU3NzE=","html_url":"https://github.com/fmeyer","type":"User","site_admin":false}
{"repo":"coursera-dl/coursera-dl","starred_at":"2012-03-21T21:07:15Z","login":"frohoff","id":6477,"node_id":"MDQ6VXNlcjY0Nzc=","html_url":"https://github.com/frohoff","type":"User","site_admin":false}
{"repo":"coursera-dl/coursera-dl","starred_at":"2012-03-21T21:07:15Z","login":"janus","id":6726,"node_id":"MDQ6VXNlcjY3MjY=","html_url":"https://github.com/janus","type":"User","site_admin":false}
{"repo":"coursera-dl/coursera-dl","starred_at":"2012-03-21T21:07:15Z","login":"shanlalit","id":6775,"node_id":"MDQ6VXNlcjY3NzU=","html_url":"https://github.com/shanlalit","type":"User","site_admin":false}
{"repo":"coursera-dl/coursera-dl","starred_at":"2012-03-21T21:07:15Z","login":"motemen","id":8465,"node_id":"MDQ6VXNlcjg0NjU=","html_url":"https://github.com/motemen","type":"User","site_admin":false}
{"repo":"coursera-dl/coursera-dl","starred_at":"2012-03-21T21:07:15Z","login":"wwwjscom","id":9424,"node_id":"MDQ6VXNlcjk0MjQ=","html_url":"https://github.com/wwwjscom","type":"User","site_admin":false}
{"repo":"coursera-dl/coursera-dl","starred_at":"2012-03-21T21:07:15Z","login":"romanz","id":9900,"node_id":"MDQ6VXNlcjk5MDA=","html_url":"https://github.com/romanz","type":"User","site_admin":false}
{"repo":"coursera-dl/coursera-dl","starred_at":"2012-03-21T21:07:15Z","login":"igrigorik","id":10652,"node_id":"MDQ6VXNlcjEwNjUy","html_url":"https://github.com/igrigorik","type":"User","site_admin":false}
{"repo":"coursera-dl/coursera-dl","starred_at":"2012-03-21T21:07:15Z","login":"chirayu","id":11241,"node_id":"MDQ6VXNlcjExMjQx","html_url":"https://github.com/chirayu","type":"User","site_admin":false}
{"repo":"coursera-dl/coursera-dl","starred_at":"2012-03-21T21:07:15Z","login":"spariev","id":12550,"node_id":"MDQ6VXNlcjEyNTUw","html_url":"https://github.com/spariev","type":"User","site_admin":false}
{"repo":"coursera-dl/coursera-dl","starred_at":"2012-03-21T21:07:15Z","login":"jonbaer","id":13155,"node_id":"MDQ6VXNlcjEzMTU1","html_url":"https://github.com/jonbaer","type":"User","site_admin":false}
{"repo":"coursera-dl/coursera-dl","starred_at":"2012-03-21T21:07:15Z","login":"itsnotvalid","id":13694,"node_id":"MDQ6VXNlcjEzNjk0","html_url":"https://github.com/itsnotvalid","type":"User","site_admin":false}
{"repo":"coursera-dl/coursera-dl","starred_at":"2012-03-21T21:07:15Z","login":"travisjeffery","id":15225,"node_id":"MDQ6VXNlcjE1MjI1","html_url":"https://github.com/travisjeffery","type":"User","site_admin":false}
{"repo":"coursera-dl/coursera-dl","starred_at":"2012-03-21T21:07:15Z","login":"kmelnikov","id":15929,"node_id":"MDQ6VXNlcjE1OTI5","html_url":"https://github.com/kmelnikov","type":"User","site_admin":false}
{"repo":"coursera-dl/coursera-dl","starred_at":"2012-03-21T21:07:15Z","login":"jemerick","id":18160,"node_id":"MDQ6VXNlcjE4MTYw","html_url":"https://github.com/jemerick","type":"User","site_admin":false}
{"repo":"coursera-dl/coursera-dl","starred_at":"2012-03-21T21:07:15Z","login":"felipehummel","id":21449,"node_id":"MDQ6VXNlcjIxNDQ5","html_url":"https://github.com/felipehummel","type":"User","site_admin":false}
{"repo":"coursera-dl/coursera-dl","starred_at":"2012-03-21T21:07:15Z","login":"amaudy","id":23410,"node_id":"MDQ6VXNlcjIzNDEw","html_url":"https://github.com/amaudy","type":"User","site_admin":false}
{"repo":"coursera-dl/coursera-dl","starred_at":"2012-03-21T21:07:15Z","login":"michaelswang","id":24325,"node_id":"MDQ6VXNlcjI0MzI1","html_url":"https://github.com/michaelswang","type":"User","site_admin":false}
{"repo":"coursera-dl/coursera-dl","starred_at":"2012-03-21T21:07:15Z","login":"haraball","id":25930,"node_id":"MDQ6VXNlcjI1OTMw","html_url":"https://github.com/haraball","type":"User","site_admin":false}
