{"repo":"gohugoio/hugo","starred_at":"2013-07-04T15:35:12Z","login":"spf13","id":173412,"node_id":"MDQ6VXNlcjE3MzQxMg==","html_url":"https://github.com/spf13","type":"User","site_admin":false}
{"repo":"gohugoio/hugo","starred_at":"2013-07-04T17:25:06Z","login":"bobthecow","id":53660,"node_id":"MDQ6VXNlcjUzNjYw","html_url":"https://github.com/bobthecow","type":"User","site_admin":false}
{"repo":"gohugoio/hugo","starred_at":"2013-07-08T06:22:38Z","login":"devogon","id":878143,"node_id":"MDQ6VXNlcjg3ODE0Mw==","html_url":"https://github.com/devogon","type":"User","site_admin":false}
{"repo":"gohugoio/hugo","starred_at":"2013-07-10T15:25:38Z","login":"robsyme","id":31576,"node_id":"MDQ6VXNlcjMxNTc2","html_url":"https://github.com/robsyme","type":"User","site_admin":false}
{"repo":"gohugoio/hugo","starred_at":"2013-07-10T16:20:46Z","login":"bkaradzic","id":814772,"node_id":"MDQ6VXNlcjgxNDc3Mg==","html_url":"https://github.com/bkaradzic","type":"User","site_admin":false}
{"repo":"gohugoio/hugo","starred_at":"2013-07-10T18:00:30Z","login":"titanous","id":13026,"node_id":"MDQ6VXNlcjEzMDI2","html_url":"https://github.com/titanous","type":"User","site_admin":false}
{"repo":"gohugoio/hugo","starred_at":"2013-07-10T18:40:26Z","login":"dsog","id":434599,"node_id":"MDQ6VXNlcjQzNDU5OQ==","html_url":"https://github.com/dsog","type":"User","site_admin":false}
{"repo":"gohugoio/hugo","starred_at":"2013-07-10T18:50:20Z","login":"nickpresta","id":49090,"node_id":"MDQ6VXNlcjQ5MDkw","html_url":"https://github.com/nickpresta","type":"User","site_admin":false}
{"repo":"gohugoio/hugo","starred_at":"2013-07-10T19:26:22Z","login":"dhirenb","id":510700,"node_id":"MDQ6VXNlcjUxMDcwMA==","html_url":"https://github.com/dhirenb","type":"User","site_admin":false}
{"repo":"gohugoio/hugo","starred_at":"2013-07-10T19:26:47Z","login":"jeberly","id":26565,"node_id":"MDQ6VXNlcjI2NTY1","html_url":"https://github.com/jeberly","type":"User","site_admin":false}
{"repo":"gohugoio/hugo","starred_at":"2013-07-10T19:41:10Z","login":"liamstask","id":51256,"node_id":"MDQ6VXNlcjUxMjU2","html_url":"https://github.com/liamstask","type":"User","site_admin":false}
{"repo":"gohugoio/hugo","starred_at":"2013-07-10T21:15:48Z","login":"ivanvanderbyl","id":24278,"node_id":"MDQ6VXNlcjI0Mjc4","html_url":"https://github.com/ivanvanderbyl","type":"User","site_admin":false}
{"repo":"gohugoio/hugo","starred_at":"2013-07-10T22:17:29Z","login":"sosedoff","id":71051,"node_id":"MDQ6VXNlcjcxMDUx","html_url":"https://github.com/sosedoff","type":"User","site_admin":false}
{"repo":"gohugoio/hugo","starred_at":"2013-07-11T02:18:56Z","login":"lidashuang","id":612381,"node_id":"MDQ6VXNlcjYxMjM4MQ==","html_url":"https://github.com/lidashuang","type":"User","site_admin":false}
{"repo":"gohugoio/hugo","starred_at":"2013-07-13T10:52:38Z","login":"hSATAC","id":88208,"node_id":"MDQ6VXNlcjg4MjA4","html_url":"https://github.com/hSATAC","type":"User","site_admin":false}
{"repo":"gohugoio/hugo","starred_at":"2013-07-13T11:05:45Z","login":"VonC","id":79478,"node_id":"MDQ6VXNlcjc5NDc4","html_url":"https://github.com/VonC","type":"User","site_admin":false}
{"repo":"gohugoio/hugo","starred_at":"2013-07-13T11:16:35Z","login":"JuanitoFatas","id":1000669,"node_id":"MDQ6VXNlcjEwMDA2Njk=","html_url":"https://github.com/JuanitoFatas","type":"User","site_admin":false}
{"repo":"gohugoio/hugo","starred_at":"2013-07-13T12:20:59Z","login":"silentnull","id":886122,"node_id":"MDQ6VXNlcjg4NjEyMg==","html_url":"https://github.com/silentnull","type":"User","site_admin":false}
{"repo":"gohugoio/hugo","starred_at":"2013-07-13T12:38:06Z","login":"KarinaLibrary","id":596177,"node_id":"MDQ6VXNlcjU5NjE3Nw==","html_url":"https://github.com/KarinaLibrary","type":"User","site_admin":false}
{"repo":"gohugoio/hugo","starred_at":"2013-07-13T17:02:07Z","login":"lzimm","id":139388,"node_id":"MDQ6VXNlcjEzOTM4OA==","html_url":"https://github.com/lzimm","type":"User","site_admin":false}
{"repo":"gohugoio/hugo","starred_at":"2013-07-13T19:09:27Z","login":"RoneyThomas","id":2186812,"node_id":"MDQ6VXNlcjIxODY4MTI=","html_url":"https://github.com/RoneyThomas","type":"User","site_admin":false}
{"repo":"gohugoio/hugo","starred_at":"2013-07-14T05:46:07Z","login":"klynton","id":104720,"node_id":"MDQ6VXNlcjEwNDcyMA==","html_url":"https://github.com/klynton","type":"User","site_admin":false}
{"repo":"gohugoio/hugo","starred_at":"2013-07-14T07:09:41Z","login":"elithrar","id":18544,"node_id":"MDQ6VXNlcjE4NTQ0","html_url":"https://github.com/elithrar","type":"User","site_admin":false}
{"repo":"gohugoio/hugo","starred_at":"2013-07-14T13:19:22Z","login":"terryh","id":172822,"node_id":"MDQ6VXNlcjE3MjgyMg==","html_url":"https://github.com/terryh","type":"User","site_admin":false}
{"repo":"gohugoio/hugo","starred_at":"2013-07-14T15:21:24Z","login":"gvatn","id":310000,"node_id":"MDQ6VXNlcjMxMDAwMA==","html_url":"https://github.com/gvatn","type":"User","site_admin":false}
{"repo":"gohugoio/hugo","starred_at":"2013-07-14T20:45:36Z","login":"mindreframer","id":1232,"node_id":"MDQ6VXNlcjEyMzI=","html_url":"https://github.com/mindreframer","type":"User","site_admin":false}
{"repo":"gohugoio/hugo","starred_at":"2013-07-15T03:43:46Z","login":"xiocode","id":1326473,"node_id":"MDQ6VXNlcjEzMjY0NzM=","html_url":"https://github.com/xiocode","type":"User","site_admin":false}
{"repo":"gohugoio/hugo","starred_at":"2013-07-22T19:06:00Z","login":"fern4lvarez","id":1381925,"node_id":"MDQ6VXNlcjEzODE5MjU=","html_url":"https://github.com/fern4lvarez","type":"User","site_admin":false}
{"repo":"gohugoio/hugo","starred_at":"2013-07-23T12:55:38Z","login":"stroborobo","id":684180,"node_id":"MDQ6VXNlcjY4NDE4MA==","html_url":"https://github.com/stroborobo","type":"User","site_admin":false}
{"repo":"gohugoio/hugo","starred_at":"2013-07-28T12:19:53Z","login":"srollyson","id":1042879,"node_id":"MDQ6VXNlcjEwNDI4Nzk=","html_url":"https://github.com/srollyson","type":"User","site_admin":false}
