{"repo":"hashicorp/vault","starred_at":"2015-04-10T18:34:57Z","login":"mitchellh","id":1299,"node_id":"MDQ6VXNlcjEyOTk=","html_url":"https://github.com/mitchellh","type":"User","site_admin":false}
{"repo":"hashicorp/vault","starred_at":"2015-04-10T18:35:52Z","login":"justincampbell","id":246978,"node_id":"MDQ6VXNlcjI0Njk3OA==","html_url":"https://github.com/justincampbell","type":"User","site_admin":false}
{"repo":"hashicorp/vault","starred_at":"2015-04-13T19:11:19Z","login":"sean-","id":349516,"node_id":"MDQ6VXNlcjM0OTUxNg==","html_url":"https://github.com/sean-","type":"User","site_admin":false}
{"repo":"hashicorp/vault","starred_at":"2015-04-16T20:32:38Z","login":"cmillward","id":391028,"node_id":"MDQ6VXNlcjM5MTAyOA==","html_url":"https://github.com/cmillward","type":"User","site_admin":false}
{"repo":"hashicorp/vault","starred_at":"2015-04-21T03:21:49Z","login":"keithchambers","id":1405432,"node_id":"MDQ6VXNlcjE0MDU0MzI=","html_url":"https://github.com/keithchambers","type":"User","site_admin":false}
{"repo":"hashicorp/vault","starred_at":"2015-04-28T17:01:03Z","login":"ryanuber","id":1642288,"node_id":"MDQ6VXNlcjE2NDIyODg=","html_url":"https://github.com/ryanuber","type":"User","site_admin":false}
{"repo":"hashicorp/vault","starred_at":"2015-04-28T17:09:24Z","login":"kyleterry","id":78383,"node_id":"MDQ6VXNlcjc4Mzgz","html_url":"https://github.com/kyleterry","type":"User","site_admin":false}
{"repo":"hashicorp/vault","starred_at":"2015-04-28T17:12:44Z","login":"extrabacon","id":1558613,"node_id":"MDQ6VXNlcjE1NTg2MTM=","html_url":"https://github.com/extrabacon","type":"User","site_admin":false}
{"repo":"hashicorp/vault","starred_at":"2015-04-28T17:16:39Z","login":"jeekajoo","id":1882534,"node_id":"MDQ6VXNlcjE4ODI1MzQ=","html_url":"https://github.com/jeekajoo","type":"User","site_admin":false}
{"repo":"hashicorp/vault","starred_at":"2015-04-28T17:17:02Z","login":"yelinaung","id":275120,"node_id":"MDQ6VXNlcjI3NTEyMA==","html_url":"https://github.com/yelinaung","type":"User","site_admin":false}
{"repo":"hashicorp/vault","starred_at":"2015-04-28T17:17:57Z","login":"igungor","id":8654,"node_id":"MDQ6VXNlcjg2NTQ=","html_url":"https://github.com/igungor","type":"User","site_admin":false}
{"repo":"hashicorp/vault","starred_at":"2015-04-28T17:19:20Z","login":"tkersey","id":217,"node_id":"MDQ6VXNlcjIxNw==","html_url":"https://github.com/tkersey","type":"User","site_admin":false}
{"repo":"hashicorp/vault","starred_at":"2015-04-28T17:19:24Z","login":"moondowner","id":1262604,"node_id":"MDQ6VXNlcjEyNjI2MDQ=","html_url":"https://github.com/moondowner","type":"User","site_admin":false}
{"repo":"hashicorp/vault","starred_at":"2015-04-28T17:20:05Z","login":"atvictor","id":1115716,"node_id":"MDQ6VXNlcjExMTU3MTY=","html_url":"https://github.com/atvictor","type":"User","site_admin":false}
{"repo":"hashicorp/vault","starred_at":"2015-04-28T17:20:32Z","login":"rtcoms","id":37205,"node_id":"MDQ6VXNlcjM3MjA1","html_url":"https://github.com/rtcoms","type":"User","site_admin":false}
{"repo":"hashicorp/vault","starred_at":"2015-04-28T17:20:47Z","login":"juliancheal","id":63991,"node_id":"MDQ6VXNlcjYzOTkx","html_url":"https://github.com/juliancheal","type":"User","site_admin":false}
{"repo":"hashicorp/vault","starred_at":"2015-04-28T17:22:01Z","login":"crohr","id":6114,"node_id":"MDQ6VXNlcjYxMTQ=","html_url":"https://github.com/crohr","type":"User","site_admin":false}
{"repo":"hashicorp/vault","starred_at":"2015-04-28T17:22:15Z","login":"markbahnman","id":197497,"node_id":"MDQ6VXNlcjE5NzQ5Nw==","html_url":"https://github.com/markbahnman","type":"User","site_admin":false}
{"repo":"hashicorp/vault","starred_at":"2015-04-28T17:22:20Z","login":"fatih","id":438920,"node_id":"MDQ6VXNlcjQzODkyMA==","html_url":"https://github.com/fatih","type":"User","site_admin":true}
{"repo":"hashicorp/vault","starred_at":"2015-04-28T17:23:02Z","login":"coox","id":494768,"node_id":"MDQ6VXNlcjQ5NDc2OA==","html_url":"https://github.com/coox","type":"User","site_admin":false}
{"repo":"hashicorp/vault","starred_at":"2015-04-28T17:23:08Z","login":"palourde","id":4105580,"node_id":"MDQ6VXNlcjQxMDU1ODA=","html_url":"https://github.com/palourde","type":"User","site_admin":false}
{"repo":"hashicorp/vault","starred_at":"2015-04-28T17:23:15Z","login":"FredericJacobs","id":400296,"node_id":"MDQ6VXNlcjQwMDI5Ng==","html_url":"https://github.com/FredericJacobs","type":"User","site_admin":false}
{"repo":"hashicorp/vault","starred_at":"2015-04-28T17:23:35Z","login":"HLT","id":1618938,"node_id":"MDQ6VXNlcjE2MTg5Mzg=","html_url":"https://github.com/HLT","type":"User","site_admin":false}
{"repo":"hashicorp/vault","starred_at":"2015-04-28T17:24:10Z","login":"dsog","id":434599,"node_id":"MDQ6VXNlcjQzNDU5OQ==","html_url":"https://github.com/dsog","type":"User","site_admin":false}
{"repo":"hashicorp/vault","starred_at":"2015-04-28T17:25:13Z","login":"mlehner","id":365438,"node_id":"MDQ6VXNlcjM2NTQzOA==","html_url":"https://github.com/mlehner","type":"User","site_admin":false}
{"repo":"hashicorp/vault","starred_at":"2015-04-28T17:25:44Z","login":"mahmoudimus","id":40820,"node_id":"MDQ6VXNlcjQwODIw","html_url":"https://github.com/mahmoudimus","type":"User","site_admin":false}
{"repo":"hashicorp/vault","starred_at":"2015-04-28T17:27:16Z","login":"jslivane","id":1262018,"node_id":"MDQ6VXNlcjEyNjIwMTg=","html_url":"https://github.com/jslivane","type":"User","site_admin":false}
{"repo":"hashicorp/vault","starred_at":"2015-04-28T17:27:41Z","login":"tonglil","id":3250776,"node_id":"MDQ6VXNlcjMyNTA3NzY=","html_url":"https://github.com/tonglil","type":"User","site_admin":false}
{"repo":"hashicorp/vault","starred_at":"2015-04-28T17:29:00Z","login":"noaheverett","id":115447,"node_id":"MDQ6VXNlcjExNTQ0Nw==","html_url":"https://github.com/noaheverett","type":"User","site_admin":false}
{"repo":"hashicorp/vault","starred_at":"2015-04-28T17:29:23Z","login":"Ginja","id":1631363,"node_id":"MDQ6VXNlcjE2MzEzNjM=","html_url":"https://github.com/Ginja","type":"User","site_admin":false}
