{"repo":"marionettejs/backbone.marionette","starred_at":"2011-12-12T16:36:09Z","login":"motiooon","id":870995,"node_id":"MDQ6VXNlcjg3MDk5NQ==","html_url":"https://github.com/motiooon","type":"User","site_admin":false}
{"repo":"marionettejs/backbone.marionette","starred_at":"2011-12-12T16:36:09Z","login":"PauCodina","id":854006,"node_id":"MDQ6VXNlcjg1NDAwNg==","html_url":"https://github.com/PauCodina","type":"User","site_admin":false}
{"repo":"marionettejs/backbone.marionette","starred_at":"2011-12-12T16:36:09Z","login":"jonmorten","id":773079,"node_id":"MDQ6VXNlcjc3MzA3OQ==","html_url":"https://github.com/jonmorten","type":"User","site_admin":false}
{"repo":"marionettejs/backbone.marionette","starred_at":"2011-12-12T16:36:09Z","login":"nerdfiles","id":102306,"node_id":"MDQ6VXNlcjEwMjMwNg==","html_url":"https://github.com/nerdfiles","type":"User","site_admin":false}
{"repo":"marionettejs/backbone.marionette","starred_at":"2011-12-12T16:36:09Z","login":"topfunky","id":26,"node_id":"MDQ6VXNlcjI2","html_url":"https://github.com/topfunky","type":"User","site_admin":false}
{"repo":"marionettejs/backbone.marionette","starred_at":"2011-12-12T16:36:09Z","login":"BrianTheCoder","id":102,"node_id":"MDQ6VXNlcjEwMg==","html_url":"https://github.com/BrianTheCoder","type":"User","site_admin":false}
{"repo":"marionettejs/backbone.marionette","starred_at":"2011-12-12T16:36:09Z","login":"lukesutton","id":109,"node_id":"MDQ6VXNlcjEwOQ==","html_url":"https://github.com/lukesutton","type":"User","site_admin":false}
{"repo":"marionettejs/backbone.marionette","starred_at":"2011-12-12T16:36:09Z","login":"joshsusser","id":156,"node_id":"MDQ6VXNlcjE1Ng==","html_url":"https://github.com/joshsusser","type":"User","site_admin":false}
{"repo":"marionettejs/backbone.marionette","starred_at":"2011-12-12T16:36:09Z","login":"zapnap","id":194,"node_id":"MDQ6VXNlcjE5NA==","html_url":"https://github.com/zapnap","type":"User","site_admin":false}
{"repo":"marionettejs/backbone.marionette","starred_at":"2011-12-12T16:36:09Z","login":"marten","id":277,"node_id":"MDQ6VXNlcjI3Nw==","html_url":"https://github.com/marten","type":"User","site_admin":false}
{"repo":"marionettejs/backbone.marionette","starred_at":"2011-12-12T16:36:09Z","login":"johnny","id":288,"node_id":"MDQ6VXNlcjI4OA==","html_url":"https://github.com/johnny","type":"User","site_admin":false}
{"repo":"marionettejs/backbone.marionette","starred_at":"2011-12-12T16:36:09Z","login":"vic","id":331,"node_id":"MDQ6VXNlcjMzMQ==","html_url":"https://github.com/vic","type":"User","site_admin":false}
{"repo":"marionettejs/backbone.marionette","starred_at":"2011-12-12T16:36:09Z","login":"jfcouture","id":490,"node_id":"MDQ6VXNlcjQ5MA==","html_url":"https://github.com/jfcouture","type":"User","site_admin":false}
{"repo":"marionettejs/backbone.marionette","starred_at":"2011-12-12T16:36:09Z","login":"japj","id":512,"node_id":"MDQ6VXNlcjUxMg==","html_url":"https://github.com/japj","type":"User","site_admin":false}
{"repo":"marionettejs/backbone.marionette","starred_at":"2011-12-12T16:36:09Z","login":"joaovitor","id":589,"node_id":"MDQ6VXNlcjU4OQ==","html_url":"https://github.com/joaovitor","type":"User","site_admin":false}
{"repo":"marionettejs/backbone.marionette","starred_at":"2011-12-12T16:36:09Z","login":"hipertracker","id":649,"node_id":"MDQ6VXNlcjY0OQ==","html_url":"https://github.com/hipertracker","type":"User","site_admin":false}
{"repo":"marionettejs/backbone.marionette","starred_at":"2011-12-12T16:36:09Z","login":"malkomalko","id":763,"node_id":"MDQ6VXNlcjc2Mw==","html_url":"https://github.com/malkomalko","type":"User","site_admin":false}
{"repo":"marionettejs/backbone.marionette","starred_at":"2011-12-12T16:36:09Z","login":"shanesveller","id":831,"node_id":"MDQ6VXNlcjgzMQ==","html_url":"https://github.com/shanesveller","type":"User","site_admin":false}
{"repo":"marionettejs/backbone.marionette","starred_at":"2011-12-12T16:36:09Z","login":"zygote","id":833,"node_id":"MDQ6VXNlcjgzMw==","html_url":"https://github.com/zygote","type":"User","site_admin":false}
{"repo":"marionettejs/backbone.marionette","starred_at":"2011-12-12T16:36:09Z","login":"ejdraper","id":910,"node_id":"MDQ6VXNlcjkxMA==","html_url":"https://github.com/ejdraper","type":"User","site_admin":false}
{"repo":"marionettejs/backbone.marionette","starred_at":"2011-12-12T16:36:09Z","login":"shenoudab","id":911,"node_id":"MDQ6VXNlcjkxMQ==","html_url":"https://github.com/shenoudab","type":"User","site_admin":false}
{"repo":"marionettejs/backbone.marionette","starred_at":"2011-12-12T16:36:09Z","login":"durdn","id":1219,"node_id":"MDQ6VXNlcjEyMTk=","html_url":"https://github.com/durdn","type":"User","site_admin":false}
{"repo":"marionettejs/backbone.marionette","starred_at":"2011-12-12T16:36:09Z","login":"alphabetum","id":1246,"node_id":"MDQ6VXNlcjEyNDY=","html_url":"https://github.com/alphabetum","type":"User","site_admin":false}
{"repo":"marionettejs/backbone.marionette","starred_at":"2011-12-12T16:36:09Z","login":"h3h","id":1401,"node_id":"MDQ6VXNlcjE0MDE=","html_url":"https://github.com/h3h","type":"User","site_admin":false}
{"repo":"marionettejs/backbone.marionette","starred_at":"2011-12-12T16:36:09Z","login":"rbarazi","id":1444,"node_id":"MDQ6VXNlcjE0NDQ=","html_url":"https://github.com/rbarazi","type":"User","site_admin":false}
{"repo":"marionettejs/backbone.marionette","starred_at":"2011-12-12T16:36:09Z","login":"number5","id":1545,"node_id":"MDQ6VXNlcjE1NDU=","html_url":"https://github.com/number5","type":"User","site_admin":false}
{"repo":"marionettejs/backbone.marionette","starred_at":"2011-12-12T16:36:09Z","login":"KevM","id":1565,"node_id":"MDQ6VXNlcjE1NjU=","html_url":"https://github.com/KevM","type":"User","site_admin":false}
{"repo":"marionettejs/backbone.marionette","starred_at":"2011-12-12T16:36:09Z","login":"raja","id":1592,"node_id":"MDQ6VXNlcjE1OTI=","html_url":"https://github.com/raja","type":"User","site_admin":false}
{"repo":"marionettejs/backbone.marionette","starred_at":"2011-12-12T16:36:09Z","login":"cw","id":1692,"node_id":"MDQ6VXNlcjE2OTI=","html_url":"https://github.com/cw","type":"User","site_admin":false}
{"repo":"marionettejs/backbone.marionette","starred_at":"2011-12-12T16:36:09Z","login":"reybango","id":1748,"node_id":"MDQ6VXNlcjE3NDg=","html_url":"https://github.com/reybango","type":"User","site_admin":false}
