{"repo":"postcss/postcss","starred_at":"2013-10-22T22:24:55Z","login":"demiazz","id":609180,"node_id":"MDQ6VXNlcjYwOTE4MA==","html_url":"https://github.com/demiazz","type":"User","site_admin":false}
{"repo":"postcss/postcss","starred_at":"2013-10-23T04:54:14Z","login":"kristerkari","id":993108,"node_id":"MDQ6VXNlcjk5MzEwOA==","html_url":"https://github.com/kristerkari","type":"User","site_admin":false}
{"repo":"postcss/postcss","starred_at":"2013-10-23T04:55:05Z","login":"Anakros","id":1309035,"node_id":"MDQ6VXNlcjEzMDkwMzU=","html_url":"https://github.com/Anakros","type":"User","site_admin":false}
{"repo":"postcss/postcss","starred_at":"2013-10-23T11:03:32Z","login":"roman01la","id":1355501,"node_id":"MDQ6VXNlcjEzNTU1MDE=","html_url":"https://github.com/roman01la","type":"User","site_admin":false}
{"repo":"postcss/postcss","starred_at":"2013-10-24T15:01:54Z","login":"nDmitry","id":2134568,"node_id":"MDQ6VXNlcjIxMzQ1Njg=","html_url":"https://github.com/nDmitry","type":"User","site_admin":false}
{"repo":"postcss/postcss","starred_at":"2013-11-02T23:19:03Z","login":"bradyvercher","id":1302030,"node_id":"MDQ6VXNlcjEzMDIwMzA=","html_url":"https://github.com/bradyvercher","type":"User","site_admin":false}
{"repo":"postcss/postcss","starred_at":"2013-11-04T19:17:20Z","login":"andreypopp","id":30594,"node_id":"MDQ6VXNlcjMwNTk0","html_url":"https://github.com/andreypopp","type":"User","site_admin":false}
{"repo":"postcss/postcss","starred_at":"2013-11-04T20:52:19Z","login":"dmitry-ilyashevich","id":37133,"node_id":"MDQ6VXNlcjM3MTMz","html_url":"https://github.com/dmitry-ilyashevich","type":"User","site_admin":false}
{"repo":"postcss/postcss","starred_at":"2013-11-04T20:58:53Z","login":"kugaevsky","id":125203,"node_id":"MDQ6VXNlcjEyNTIwMw==","html_url":"https://github.com/kugaevsky","type":"User","site_admin":false}
{"repo":"postcss/postcss","starred_at":"2013-11-04T21:41:29Z","login":"derekr","id":22249,"node_id":"MDQ6VXNlcjIyMjQ5","html_url":"https://github.com/derekr","type":"User","site_admin":false}
{"repo":"postcss/postcss","starred_at":"2013-11-04T22:13:39Z","login":"sindresorhus","id":170270,"node_id":"MDQ6VXNlcjE3MDI3MA==","html_url":"https://github.com/sindresorhus","type":"User","site_admin":false}
{"repo":"postcss/postcss","starred_at":"2013-11-04T22:16:18Z","login":"skiant","id":724736,"node_id":"MDQ6VXNlcjcyNDczNg==","html_url":"https://github.com/skiant","type":"User","site_admin":false}
{"repo":"postcss/postcss","starred_at":"2013-11-04T22:21:44Z","login":"tbranyen","id":181635,"node_id":"MDQ6VXNlcjE4MTYzNQ==","html_url":"https://github.com/tbranyen","type":"User","site_admin":false}
{"repo":"postcss/postcss","starred_at":"2013-11-04T22:28:30Z","login":"indieisaconcept","id":640613,"node_id":"MDQ6VXNlcjY0MDYxMw==","html_url":"https://github.com/indieisaconcept","type":"User","site_admin":false}
{"repo":"postcss/postcss","starred_at":"2013-11-04T22:32:19Z","login":"grydstedt","id":782394,"node_id":"MDQ6VXNlcjc4MjM5NA==","html_url":"https://github.com/grydstedt","type":"User","site_admin":false}
{"repo":"postcss/postcss","starred_at":"2013-11-04T23:10:17Z","login":"Ragnarokkr","id":893472,"node_id":"MDQ6VXNlcjg5MzQ3Mg==","html_url":"https://github.com/Ragnarokkr","type":"User","site_admin":false}
{"repo":"postcss/postcss","starred_at":"2013-11-04T23:20:08Z","login":"faceleg","id":1000759,"node_id":"MDQ6VXNlcjEwMDA3NTk=","html_url":"https://github.com/faceleg","type":"User","site_admin":false}
{"repo":"postcss/postcss","starred_at":"2013-11-05T00:23:18Z","login":"blakeembrey","id":1088987,"node_id":"MDQ6VXNlcjEwODg5ODc=","html_url":"https://github.com/blakeembrey","type":"User","site_admin":false}
{"repo":"postcss/postcss","starred_at":"2013-11-05T02:21:00Z","login":"switer","id":1167668,"node_id":"MDQ6VXNlcjExNjc2Njg=","html_url":"https://github.com/switer","type":"User","site_admin":false}
{"repo":"postcss/postcss","starred_at":"2013-11-05T04:43:10Z","login":"cbmd","id":196139,"node_id":"MDQ6VXNlcjE5NjEzOQ==","html_url":"https://github.com/cbmd","type":"User","site_admin":false}
{"repo":"postcss/postcss","starred_at":"2013-11-05T06:41:50Z","login":"Lauricio","id":2200004,"node_id":"MDQ6VXNlcjIyMDAwMDQ=","html_url":"https://github.com/Lauricio","type":"User","site_admin":false}
{"repo":"postcss/postcss","starred_at":"2013-11-05T07:28:52Z","login":"afitiskin","id":204739,"node_id":"MDQ6VXNlcjIwNDczOQ==","html_url":"https://github.com/afitiskin","type":"User","site_admin":false}
{"repo":"postcss/postcss","starred_at":"2013-11-05T08:25:55Z","login":"der-On","id":359399,"node_id":"MDQ6VXNlcjM1OTM5OQ==","html_url":"https://github.com/der-On","type":"User","site_admin":false}
{"repo":"postcss/postcss","starred_at":"2013-11-05T08:33:55Z","login":"benjohnston","id":1205067,"node_id":"MDQ6VXNlcjEyMDUwNjc=","html_url":"https://github.com/benjohnston","type":"User","site_admin":false}
{"repo":"postcss/postcss","starred_at":"2013-11-05T08:54:09Z","login":"Rowno","id":605501,"node_id":"MDQ6VXNlcjYwNTUwMQ==","html_url":"https://github.com/Rowno","type":"User","site_admin":false}
{"repo":"postcss/postcss","starred_at":"2013-11-05T15:05:26Z","login":"AgtLucas","id":1909761,"node_id":"MDQ6VXNlcjE5MDk3NjE=","html_url":"https://github.com/AgtLucas","type":"User","site_admin":false}
{"repo":"postcss/postcss","starred_at":"2013-11-05T17:45:16Z","login":"basham","id":347558,"node_id":"MDQ6VXNlcjM0NzU1OA==","html_url":"https://github.com/basham","type":"User","site_admin":false}
{"repo":"postcss/postcss","starred_at":"2013-11-05T19:20:02Z","login":"paulyoung","id":84700,"node_id":"MDQ6VXNlcjg0NzAw","html_url":"https://github.com/paulyoung","type":"User","site_admin":false}
{"repo":"postcss/postcss","starred_at":"2013-11-05T20:13:14Z","login":"princed","id":796050,"node_id":"MDQ6VXNlcjc5NjA1MA==","html_url":"https://github.com/princed","type":"User","site_admin":false}
{"repo":"postcss/postcss","starred_at":"2013-11-06T01:09:37Z","login":"haroldo-ok","id":1457465,"node_id":"MDQ6VXNlcjE0NTc0NjU=","html_url":"https://github.com/haroldo-ok","type":"User","site_admin":false}
