{"repo":"resque/resque","starred_at":"2009-08-12T00:27:35Z","login":"mojombo","id":1,"node_id":"MDQ6VXNlcjE=","html_url":"https://github.com/mojombo","type":"User","site_admin":false}
{"repo":"resque/resque","starred_at":"2009-08-12T00:27:35Z","login":"defunkt","id":2,"node_id":"MDQ6VXNlcjI=","html_url":"https://github.com/defunkt","type":"User","site_admin":false}
{"repo":"resque/resque","starred_at":"2009-08-12T00:27:35Z","login":"vanpelt","id":17,"node_id":"MDQ6VXNlcjE3","html_url":"https://github.com/vanpelt","type":"User","site_admin":false}
{"repo":"resque/resque","starred_at":"2009-08-12T00:27:35Z","login":"brynary","id":19,"node_id":"MDQ6VXNlcjE5","html_url":"https://github.com/brynary","type":"User","site_admin":false}
{"repo":"resque/resque","starred_at":"2009-08-12T00:27:35Z","login":"technoweenie","id":21,"node_id":"MDQ6VXNlcjIx","html_url":"https://github.com/technoweenie","type":"User","site_admin":false}
{"repo":"resque/resque","starred_at":"2009-08-12T00:27:35Z","login":"caged","id":25,"node_id":"MDQ6VXNlcjI1","html_url":"https://github.com/caged","type":"User","site_admin":false}
{"repo":"resque/resque","starred_at":"2009-08-12T00:27:35Z","login":"topfunky","id":26,"node_id":"MDQ6VXNlcjI2","html_url":"https://github.com/topfunky","type":"User","site_admin":false}
{"repo":"resque/resque","starred_at":"2009-08-12T00:27:35Z","login":"jamesgolick","id":37,"node_id":"MDQ6VXNlcjM3","html_url":"https://github.com/jamesgolick","type":"User","site_admin":false}
{"repo":"resque/resque","starred_at":"2009-08-12T00:27:35Z","login":"atmos","id":38,"node_id":"MDQ6VXNlcjM4","html_url":"https://github.com/atmos","type":"User","site_admin":false}
{"repo":"resque/resque","starred_at":"2009-08-12T00:27:35Z","login":"mojodna","id":45,"node_id":"MDQ6VXNlcjQ1","html_url":"https://github.com/mojodna","type":"User","site_admin":false}
{"repo":"resque/resque","starred_at":"2009-08-12T00:27:35Z","login":"jnewland","id":47,"node_id":"MDQ6VXNlcjQ3","html_url":"https://github.com/jnewland","type":"User","site_admin":true}
{"repo":"resque/resque","starred_at":"2009-08-12T00:27:35Z","login":"joshknowles","id":48,"node_id":"MDQ6VXNlcjQ4","html_url":"https://github.com/joshknowles","type":"User","site_admin":false}
{"repo":"resque/resque","starred_at":"2009-08-12T00:27:35Z","login":"schacon","id":70,"node_id":"MDQ6VXNlcjcw","html_url":"https://github.com/schacon","type":"User","site_admin":false}
{"repo":"resque/resque","starred_at":"2009-08-12T00:27:35Z","login":"benburkert","id":77,"node_id":"MDQ6VXNlcjc3","html_url":"https://github.com/benburkert","type":"User","site_admin":false}
{"repo":"resque/resque","starred_at":"2009-08-12T00:27:35Z","login":"jsierles","id":82,"node_id":"MDQ6VXNlcjgy","html_url":"https://github.com/jsierles","type":"User","site_admin":false}
{"repo":"resque/resque","starred_at":"2009-08-12T00:27:35Z","login":"sr","id":90,"node_id":"MDQ6VXNlcjkw","html_url":"https://github.com/sr","type":"User","site_admin":false}
{"repo":"resque/resque","starred_at":"2009-08-12T00:27:35Z","login":"BrianTheCoder","id":102,"node_id":"MDQ6VXNlcjEwMg==","html_url":"https://github.com/BrianTheCoder","type":"User","site_admin":false}
{"repo":"resque/resque","starred_at":"2009-08-12T00:27:35Z","login":"lancecarlson","id":107,"node_id":"MDQ6VXNlcjEwNw==","html_url":"https://github.com/lancecarlson","type":"User","site_admin":false}
{"repo":"resque/resque","starred_at":"2009-08-12T00:27:35Z","login":"mattetti","id":113,"node_id":"MDQ6VXNlcjExMw==","html_url":"https://github.com/mattetti","type":"User","site_admin":false}
{"repo":"resque/resque","starred_at":"2009-08-12T00:27:35Z","login":"heavysixer","id":123,"node_id":"MDQ6VXNlcjEyMw==","html_url":"https://github.com/heavysixer","type":"User","site_admin":false}
{"repo":"resque/resque","starred_at":"2009-08-12T00:27:35Z","login":"dstrelau","id":131,"node_id":"MDQ6VXNlcjEzMQ==","html_url":"https://github.com/dstrelau","type":"User","site_admin":false}
{"repo":"resque/resque","starred_at":"2009-08-12T00:27:35Z","login":"rbazinet","id":170,"node_id":"MDQ6VXNlcjE3MA==","html_url":"https://github.com/rbazinet","type":"User","site_admin":false}
{"repo":"resque/resque","starred_at":"2009-08-12T00:27:35Z","login":"bkeepers","id":173,"node_id":"MDQ6VXNlcjE3Mw==","html_url":"https://github.com/bkeepers","type":"User","site_admin":false}
{"repo":"resque/resque","starred_at":"2009-08-12T00:27:35Z","login":"samgranieri","id":180,"node_id":"MDQ6VXNlcjE4MA==","html_url":"https://github.com/samgranieri","type":"User","site_admin":false}
{"repo":"resque/resque","starred_at":"2009-08-12T00:27:35Z","login":"mtodd","id":182,"node_id":"MDQ6VXNlcjE4Mg==","html_url":"https://github.com/mtodd","type":"User","site_admin":true}
{"repo":"resque/resque","starred_at":"2009-08-12T00:27:35Z","login":"zapnap","id":194,"node_id":"MDQ6VXNlcjE5NA==","html_url":"https://github.com/zapnap","type":"User","site_admin":false}
{"repo":"resque/resque","starred_at":"2009-08-12T00:27:35Z","login":"ELLIOTTCABLE","id":200,"node_id":"MDQ6VXNlcjIwMA==","html_url":"https://github.com/ELLIOTTCABLE","type":"User","site_admin":false}
{"repo":"resque/resque","starred_at":"2009-08-12T00:27:35Z","login":"jseifer","id":204,"node_id":"MDQ6VXNlcjIwNA==","html_url":"https://github.com/jseifer","type":"User","site_admin":false}
{"repo":"resque/resque","starred_at":"2009-08-12T00:27:35Z","login":"rdempsey","id":224,"node_id":"MDQ6VXNlcjIyNA==","html_url":"https://github.com/rdempsey","type":"User","site_admin":false}
{"repo":"resque/resque","starred_at":"2009-08-12T00:27:35Z","login":"scharfie","id":230,"node_id":"MDQ6VXNlcjIzMA==","html_url":"https://github.com/scharfie","type":"User","site_admin":false}
