{"repo":"tensorflow/tensorflow","starred_at":"2015-11-09T13:17:30Z","login":"mrry","id":192142,"node_id":"MDQ6VXNlcjE5MjE0Mg==","html_url":"https://github.com/mrry","type":"User","site_admin":false}
{"repo":"tensorflow/tensorflow","starred_at":"2015-11-09T13:18:49Z","login":"danbri","id":170265,"node_id":"MDQ6VXNlcjE3MDI2NQ==","html_url":"https://github.com/danbri","type":"User","site_admin":false}
{"repo":"tensorflow/tensorflow","starred_at":"2015-11-09T13:40:12Z","login":"rockt","id":1196835,"node_id":"MDQ6VXNlcjExOTY4MzU=","html_url":"https://github.com/rockt","type":"User","site_admin":false}
{"repo":"tensorflow/tensorflow","starred_at":"2015-11-09T13:40:58Z","login":"petro-rudenko","id":1121987,"node_id":"MDQ6VXNlcjExMjE5ODc=","html_url":"https://github.com/petro-rudenko","type":"User","site_admin":false}
{"repo":"tensorflow/tensorflow","starred_at":"2015-11-09T13:43:18Z","login":"kudkudak","id":1571945,"node_id":"MDQ6VXNlcjE1NzE5NDU=","html_url":"https://github.com/kudkudak","type":"User","site_admin":false}
{"repo":"tensorflow/tensorflow","starred_at":"2015-11-09T13:45:23Z","login":"bennokr","id":994319,"node_id":"MDQ6VXNlcjk5NDMxOQ==","html_url":"https://github.com/bennokr","type":"User","site_admin":false}
{"repo":"tensorflow/tensorflow","starred_at":"2015-11-09T13:50:09Z","login":"bryandeng","id":1997800,"node_id":"MDQ6VXNlcjE5OTc4MDA=","html_url":"https://github.com/bryandeng","type":"User","site_admin":false}
{"repo":"tensorflow/tensorflow","starred_at":"2015-11-09T13:51:52Z","login":"Kaixhin","id":991891,"node_id":"MDQ6VXNlcjk5MTg5MQ==","html_url":"https://github.com/Kaixhin","type":"User","site_admin":false}
{"repo":"tensorflow/tensorflow","starred_at":"2015-11-09T13:56:35Z","login":"dennybritz","id":403133,"node_id":"MDQ6VXNlcjQwMzEzMw==","html_url":"https://github.com/dennybritz","type":"User","site_admin":false}
{"repo":"tensorflow/tensorflow","starred_at":"2015-11-09T13:59:18Z","login":"cameronphchen","id":2787602,"node_id":"MDQ6VXNlcjI3ODc2MDI=","html_url":"https://github.com/cameronphchen","type":"User","site_admin":false}
{"repo":"tensorflow/tensorflow","starred_at":"2015-11-09T14:01:12Z","login":"mblondel","id":233706,"node_id":"MDQ6VXNlcjIzMzcwNg==","html_url":"https://github.com/mblondel","type":"User","site_admin":false}
{"repo":"tensorflow/tensorflow","starred_at":"2015-11-09T14:02:58Z","login":"shuokay","id":5029591,"node_id":"MDQ6VXNlcjUwMjk1OTE=","html_url":"https://github.com/shuokay","type":"User","site_admin":false}
{"repo":"tensorflow/tensorflow","starred_at":"2015-11-09T14:03:18Z","login":"knighter","id":985072,"node_id":"MDQ6VXNlcjk4NTA3Mg==","html_url":"https://github.com/knighter","type":"User","site_admin":false}
{"repo":"tensorflow/tensorflow","starred_at":"2015-11-09T14:03:33Z","login":"mathetian","id":4220102,"node_id":"MDQ6VXNlcjQyMjAxMDI=","html_url":"https://github.com/mathetian","type":"User","site_admin":false}
{"repo":"tensorflow/tensorflow","starred_at":"2015-11-09T14:03:34Z","login":"ice-melon","id":2037719,"node_id":"MDQ6VXNlcjIwMzc3MTk=","html_url":"https://github.com/ice-melon","type":"User","site_admin":false}
{"repo":"tensorflow/tensorflow","starred_at":"2015-11-09T14:05:10Z","login":"filipre","id":8502198,"node_id":"MDQ6VXNlcjg1MDIxOTg=","html_url":"https://github.com/filipre","type":"User","site_admin":false}
{"repo":"tensorflow/tensorflow","starred_at":"2015-11-09T14:05:57Z","login":"timgluz","id":1223889,"node_id":"MDQ6VXNlcjEyMjM4ODk=","html_url":"https://github.com/timgluz","type":"User","site_admin":false}
{"repo":"tensorflow/tensorflow","starred_at":"2015-11-09T14:06:10Z","login":"zlmzju","id":10279606,"node_id":"MDQ6VXNlcjEwMjc5NjA2","html_url":"https://github.com/zlmzju","type":"User","site_admin":false}
{"repo":"tensorflow/tensorflow","starred_at":"2015-11-09T14:06:45Z","login":"Florian-kun","id":3392187,"node_id":"MDQ6VXNlcjMzOTIxODc=","html_url":"https://github.com/Florian-kun","type":"User","site_admin":false}
{"repo":"tensorflow/tensorflow","starred_at":"2015-11-09T14:07:12Z","login":"ncb000gt","id":62615,"node_id":"MDQ6VXNlcjYyNjE1","html_url":"https://github.com/ncb000gt","type":"User","site_admin":false}
{"repo":"tensorflow/tensorflow","starred_at":"2015-11-09T14:08:40Z","login":"duguyue100","id":939553,"node_id":"MDQ6VXNlcjkzOTU1Mw==","html_url":"https://github.com/duguyue100","type":"User","site_admin":false}
{"repo":"tensorflow/tensorflow","starred_at":"2015-11-09T14:09:44Z","login":"phisiart","id":4835507,"node_id":"MDQ6VXNlcjQ4MzU1MDc=","html_url":"https://github.com/phisiart","type":"User","site_admin":false}
{"repo":"tensorflow/tensorflow","starred_at":"2015-11-09T14:10:13Z","login":"visionnet","id":1253786,"node_id":"MDQ6VXNlcjEyNTM3ODY=","html_url":"https://github.com/visionnet","type":"User","site_admin":false}
{"repo":"tensorflow/tensorflow","starred_at":"2015-11-09T14:10:21Z","login":"dittos","id":2622,"node_id":"MDQ6VXNlcjI2MjI=","html_url":"https://github.com/dittos","type":"User","site_admin":false}
{"repo":"tensorflow/tensorflow","starred_at":"2015-11-09T14:11:03Z","login":"bigwhite","id":419088,"node_id":"MDQ6VXNlcjQxOTA4OA==","html_url":"https://github.com/bigwhite","type":"User","site_admin":false}
{"repo":"tensorflow/tensorflow","starred_at":"2015-11-09T14:11:28Z","login":"craigcitro","id":468559,"node_id":"MDQ6VXNlcjQ2ODU1OQ==","html_url":"https://github.com/craigcitro","type":"User","site_admin":false}
{"repo":"tensorflow/tensorflow","starred_at":"2015-11-09T14:11:51Z","login":"tiddler","id":9299201,"node_id":"MDQ6VXNlcjkyOTkyMDE=","html_url":"https://github.com/tiddler","type":"User","site_admin":false}
{"repo":"tensorflow/tensorflow","starred_at":"2015-11-09T14:12:11Z","login":"girving","id":70511,"node_id":"MDQ6VXNlcjcwNTEx","html_url":"https://github.com/girving","type":"User","site_admin":false}
{"repo":"tensorflow/tensorflow","starred_at":"2015-11-09T14:13:08Z","login":"shovon","id":284576,"node_id":"MDQ6VXNlcjI4NDU3Ng==","html_url":"https://github.com/shovon","type":"User","site_admin":false}
{"repo":"tensorflow/tensorflow","starred_at":"2015-11-09T14:14:16Z","login":"kyunghyuncho","id":4028979,"node_id":"MDQ6VXNlcjQwMjg5Nzk=","html_url":"https://github.com/kyunghyuncho","type":"User","site_admin":false}
