{"repo":"yahoo/pure","starred_at":"2013-05-25T01:08:02Z","login":"ericf","id":29096,"node_id":"MDQ6VXNlcjI5MDk2","html_url":"https://github.com/ericf","type":"User","site_admin":false}
{"repo":"yahoo/pure","starred_at":"2013-05-27T22:44:27Z","login":"juandopazo","id":347002,"node_id":"MDQ6VXNlcjM0NzAwMg==","html_url":"https://github.com/juandopazo","type":"User","site_admin":false}
{"repo":"yahoo/pure","starred_at":"2013-05-27T23:00:39Z","login":"tilomitra","id":174783,"node_id":"MDQ6VXNlcjE3NDc4Mw==","html_url":"https://github.com/tilomitra","type":"User","site_admin":false}
{"repo":"yahoo/pure","starred_at":"2013-05-28T13:11:25Z","login":"mjadobson","id":787996,"node_id":"MDQ6VXNlcjc4Nzk5Ng==","html_url":"https://github.com/mjadobson","type":"User","site_admin":false}
{"repo":"yahoo/pure","starred_at":"2013-05-28T13:11:52Z","login":"g1","id":190395,"node_id":"MDQ6VXNlcjE5MDM5NQ==","html_url":"https://github.com/g1","type":"User","site_admin":false}
{"repo":"yahoo/pure","starred_at":"2013-05-28T13:14:08Z","login":"killercup","id":20063,"node_id":"MDQ6VXNlcjIwMDYz","html_url":"https://github.com/killercup","type":"User","site_admin":false}
{"repo":"yahoo/pure","starred_at":"2013-05-28T13:15:04Z","login":"filipeoliveiraa","id":285038,"node_id":"MDQ6VXNlcjI4NTAzOA==","html_url":"https://github.com/filipeoliveiraa","type":"User","site_admin":false}
{"repo":"yahoo/pure","starred_at":"2013-05-28T13:23:43Z","login":"fusedreality","id":440657,"node_id":"MDQ6VXNlcjQ0MDY1Nw==","html_url":"https://github.com/fusedreality","type":"User","site_admin":false}
{"repo":"yahoo/pure","starred_at":"2013-05-28T13:25:22Z","login":"LoonyPandora","id":53843,"node_id":"MDQ6VXNlcjUzODQz","html_url":"https://github.com/LoonyPandora","type":"User","site_admin":false}
{"repo":"yahoo/pure","starred_at":"2013-05-28T13:25:57Z","login":"winestock","id":989526,"node_id":"MDQ6VXNlcjk4OTUyNg==","html_url":"https://github.com/winestock","type":"User","site_admin":false}
{"repo":"yahoo/pure","starred_at":"2013-05-28T13:26:22Z","login":"naturalui","id":1953861,"node_id":"MDQ6VXNlcjE5NTM4NjE=","html_url":"https://github.com/naturalui","type":"User","site_admin":false}
{"repo":"yahoo/pure","starred_at":"2013-05-28T13:27:51Z","login":"jimmysawczuk","id":590736,"node_id":"MDQ6VXNlcjU5MDczNg==","html_url":"https://github.com/jimmysawczuk","type":"User","site_admin":false}
{"repo":"yahoo/pure","starred_at":"2013-05-28T13:29:26Z","login":"haraball","id":25930,"node_id":"MDQ6VXNlcjI1OTMw","html_url":"https://github.com/haraball","type":"User","site_admin":false}
{"repo":"yahoo/pure","starred_at":"2013-05-28T13:31:01Z","login":"beshur","id":532273,"node_id":"MDQ6VXNlcjUzMjI3Mw==","html_url":"https://github.com/beshur","type":"User","site_admin":false}
{"repo":"yahoo/pure","starred_at":"2013-05-28T13:37:58Z","login":"georgiee","id":1701755,"node_id":"MDQ6VXNlcjE3MDE3NTU=","html_url":"https://github.com/georgiee","type":"User","site_admin":false}
{"repo":"yahoo/pure","starred_at":"2013-05-28T13:39:06Z","login":"jeremyvdw","id":3919,"node_id":"MDQ6VXNlcjM5MTk=","html_url":"https://github.com/jeremyvdw","type":"User","site_admin":false}
{"repo":"yahoo/pure","starred_at":"2013-05-28T13:39:32Z","login":"frozzare","id":14610,"node_id":"MDQ6VXNlcjE0NjEw","html_url":"https://github.com/frozzare","type":"User","site_admin":false}
{"repo":"yahoo/pure","starred_at":"2013-05-28T13:42:15Z","login":"sligodave","id":200353,"node_id":"MDQ6VXNlcjIwMDM1Mw==","html_url":"https://github.com/sligodave","type":"User","site_admin":false}
{"repo":"yahoo/pure","starred_at":"2013-05-28T13:45:33Z","login":"jordanjustice","id":1316479,"node_id":"MDQ6VXNlcjEzMTY0Nzk=","html_url":"https://github.com/jordanjustice","type":"User","site_admin":false}
{"repo":"yahoo/pure","starred_at":"2013-05-28T13:46:04Z","login":"Braunson","id":577273,"node_id":"MDQ6VXNlcjU3NzI3Mw==","html_url":"https://github.com/Braunson","type":"User","site_admin":false}
{"repo":"yahoo/pure","starred_at":"2013-05-28T13:46:53Z","login":"iFloris","id":252882,"node_id":"MDQ6VXNlcjI1Mjg4Mg==","html_url":"https://github.com/iFloris","type":"User","site_admin":false}
{"repo":"yahoo/pure","starred_at":"2013-05-28T13:47:23Z","login":"gnclmorais","id":385232,"node_id":"MDQ6VXNlcjM4NTIzMg==","html_url":"https://github.com/gnclmorais","type":"User","site_admin":false}
{"repo":"yahoo/pure","starred_at":"2013-05-28T13:47:58Z","login":"ckurdziel","id":818797,"node_id":"MDQ6VXNlcjgxODc5Nw==","html_url":"https://github.com/ckurdziel","type":"User","site_admin":false}
{"repo":"yahoo/pure","starred_at":"2013-05-28T13:49:54Z","login":"studiomohawk","id":28534,"node_id":"MDQ6VXNlcjI4NTM0","html_url":"https://github.com/studiomohawk","type":"User","site_admin":false}
{"repo":"yahoo/pure","starred_at":"2013-05-28T13:59:26Z","login":"pungoyal","id":42866,"node_id":"MDQ6VXNlcjQyODY2","html_url":"https://github.com/pungoyal","type":"User","site_admin":false}
{"repo":"yahoo/pure","starred_at":"2013-05-28T13:59:58Z","login":"extesy","id":65872,"node_id":"MDQ6VXNlcjY1ODcy","html_url":"https://github.com/extesy","type":"User","site_admin":false}
{"repo":"yahoo/pure","starred_at":"2013-05-28T14:00:34Z","login":"gabrielluong","id":1190888,"node_id":"MDQ6VXNlcjExOTA4ODg=","html_url":"https://github.com/gabrielluong","type":"User","site_admin":false}
{"repo":"yahoo/pure","starred_at":"2013-05-28T14:00:39Z","login":"nkrumm","id":1273758,"node_id":"MDQ6VXNlcjEyNzM3NTg=","html_url":"https://github.com/nkrumm","type":"User","site_admin":false}
{"repo":"yahoo/pure","starred_at":"2013-05-28T14:00:39Z","login":"SaitoWu","id":348915,"node_id":"MDQ6VXNlcjM0ODkxNQ==","html_url":"https://github.com/SaitoWu","type":"User","site_admin":false}
{"repo":"yahoo/pure","starred_at":"2013-05-28T14:00:44Z","login":"tylerhowarth","id":56019,"node_id":"MDQ6VXNlcjU2MDE5","html_url":"https://github.com/tylerhowarth","type":"User","site_admin":false}
